djangoldp_cqcm_map/__init__.py
djangoldp_cqcm_map/admin.py
djangoldp_cqcm_map/apps.py
djangoldp_cqcm_map/djangoldp_urls.py
djangoldp_cqcm_map/views.py
djangoldp_cqcm_map/fixtures/cqcm_poles.json
djangoldp_cqcm_map/migrations/0001_initial.py
djangoldp_cqcm_map/migrations/0002_alter_location_address_alter_location_lat_and_more.py
djangoldp_cqcm_map/migrations/0003_pole_published.py
djangoldp_cqcm_map/migrations/0004_pole_creator_mail_pole_creator_name.py
djangoldp_cqcm_map/migrations/__init__.py
djangoldp_cqcm_map/models/__base.py
djangoldp_cqcm_map/models/__init__.py
djangoldp_cqcm_map/models/cqcm_location.py
djangoldp_cqcm_map/models/cqcm_pole.py
djangoldp_cqcm_map/models/cqcm_service.py
djangoldp_cqcm_map/models/cqcm_social_network.py
djangoldp_cqcm_map/models/cqcm_structure_kind.py
djangoldp_cqcm_map/models/zzz_signals.py
djangoldp_cqcm_map-1.0.5.dist-info/METADATA
djangoldp_cqcm_map-1.0.5.dist-info/WHEEL
djangoldp_cqcm_map-1.0.5.dist-info/top_level.txt
djangoldp_cqcm_map-1.0.5.dist-info/RECORD
