Metadata-Version: 2.1
Name: djangoldp-cqcm-map
Version: 1.0.5
Summary: djangoldp package for CQCM Map
Home-page: https://git.startinblox.com/djangoldp-packages/djangoldp-cqcm-map
Author: Startinblox
Author-email: jbaptiste@startinblox.com
License: MIT
Classifier: Programming Language :: Python :: 3
Requires-Dist: djangoldp~=4.0.0
Provides-Extra: include_package_data
Requires-Dist: True; extra == "include-package-data"
